iclr_downloader/core.py
iclr_downloader/commands/download_by_year.py
icrl_downloader-0.1.0.dist-info/METADATA
icrl_downloader-0.1.0.dist-info/WHEEL
icrl_downloader-0.1.0.dist-info/top_level.txt
icrl_downloader-0.1.0.dist-info/RECORD
