Metadata-Version: 2.2
Name: icrl-downloader
Version: 0.1.0
Summary: Add your description here
Requires-Python: >=3.11.5
Requires-Dist: openreview-py>=1.47.1
Requires-Dist: sienna>=0.2.6
